png_header_injector
